{
    "fluentMethods": true,
    "relationships": [
        {
            "relationshipType": "one-to-many",
            "relationshipName": "fundingRequests",
            "otherEntityName": "fundingRequest",
            "otherEntityRelationshipName": "fundingRequestType"
        }
    ],
    "fields": [
        {
            "fieldName": "name",
            "fieldType": "String",
            "fieldValidateRules": [
                "required",
                "maxlength"
            ],
            "fieldValidateRulesMaxlength": 50
        },
        {
            "fieldName": "code",
            "fieldType": "String",
            "fieldValidateRules": [
                "required",
                "maxlength"
            ],
            "fieldValidateRulesMaxlength": 30
        }
    ],
    "changelogDate": "20170705215250",
    "entityTableName": "cf_funding_request_type",
    "dto": "mapstruct",
    "pagination": "pagination",
    "service": "serviceClass",
    "microserviceName": "carmesfnmservice",
    "searchEngine": "elasticsearch"
}